setup.py
uvml/__init__.py
uvml/afm.py
uvml/cryo.py
uvml/dissociation.py
uvml/instruments.py
uvml/template_instrument.py
uvml.egg-info/PKG-INFO
uvml.egg-info/SOURCES.txt
uvml.egg-info/dependency_links.txt
uvml.egg-info/not-zip-safe
uvml.egg-info/top_level.txt