Metadata-Version: 1.0
Name: uvml
Version: 0.24
Summary: UVML Lab Code
Home-page: https://github.com/mbe9a/uvml
Author: Michael Eller
Author-email: mbe9a@virginia.edu
License: MIT
Platform: UNKNOWN
